thumbor_wand_engine/__init__.py
thumbor_wand_engine/engine.py
thumbor_wand_engine-0.1.1.dist-info/LICENSE
thumbor_wand_engine-0.1.1.dist-info/METADATA
thumbor_wand_engine-0.1.1.dist-info/WHEEL
thumbor_wand_engine-0.1.1.dist-info/top_level.txt
thumbor_wand_engine-0.1.1.dist-info/RECORD
