Metadata-Version: 2.1
Name: thumbor-wand-engine
Version: 0.1.1
Summary: ImageMagick imaging engine for Thumbor
Home-page: https://github.com/scorphus/thumbor-wand-engine
Author: Pablo S. Blum de Aguiar
Author-email: scorphus@gmail.com
License: MIT
Keywords: thumbor imaging imagemagick magickwand magick wand
Platform: UNKNOWN
Classifier: Development Status :: 3 - Alpha
Classifier: Intended Audience :: Developers
Classifier: Intended Audience :: System Administrators
Classifier: License :: OSI Approved :: MIT License
Classifier: Natural Language :: English
Classifier: Operating System :: MacOS
Classifier: Operating System :: POSIX :: Linux
Classifier: Programming Language :: Python :: 3
Classifier: Programming Language :: Python :: 3.7
Classifier: Programming Language :: Python :: 3.8
Classifier: Programming Language :: Python :: 3.9
Classifier: Programming Language :: Python :: 3.10
Classifier: Programming Language :: Python :: 3 :: Only
Classifier: Programming Language :: Python :: Implementation :: CPython
Classifier: Topic :: Internet :: WWW/HTTP :: Dynamic Content
Classifier: Topic :: Multimedia :: Graphics :: Presentation
Classifier: Environment :: Plugins
Requires-Dist: thumbor
Requires-Dist: Wand
Provides-Extra: tests
Requires-Dist: black ; extra == 'tests'
Requires-Dist: colorama ; extra == 'tests'
Requires-Dist: flake8 ; extra == 'tests'
Requires-Dist: isort ; extra == 'tests'
Requires-Dist: pytest ; extra == 'tests'
Requires-Dist: pytest-cov ; extra == 'tests'
Requires-Dist: pytest-mock ; extra == 'tests'
Requires-Dist: twine ; extra == 'tests'
Requires-Dist: wheel ; extra == 'tests'
